apachelogs/__init__.py
apachelogs/directives.py
apachelogs/errors.py
apachelogs/parser.py
apachelogs/strftime.py
apachelogs/timeutil.py
apachelogs/util.py
apachelogs-0.6.1.dist-info/METADATA
apachelogs-0.6.1.dist-info/WHEEL
apachelogs-0.6.1.dist-info/licenses/LICENSE
apachelogs-0.6.1.dist-info/RECORD
