Metadata-Version: 2.3
Name: apachelogs
Version: 0.6.1
Summary: Parse Apache access logs
Project-URL: Source Code, https://github.com/jwodder/apachelogs
Project-URL: Bug Tracker, https://github.com/jwodder/apachelogs/issues
Project-URL: Documentation, https://apachelogs.readthedocs.io
Author-email: John Thorvald Wodder II <apachelogs@varonathe.org>
License: MIT
Keywords: Apache,access logs,httpd,logfiles
Classifier: Intended Audience :: System Administrators
Classifier: License :: OSI Approved :: MIT License
Classifier: Programming Language :: Python :: 3
Classifier: Programming Language :: Python :: 3 :: Only
Classifier: Programming Language :: Python :: 3.8
Classifier: Programming Language :: Python :: 3.9
Classifier: Programming Language :: Python :: 3.10
Classifier: Programming Language :: Python :: 3.11
Classifier: Programming Language :: Python :: 3.12
Classifier: Programming Language :: Python :: 3.13
Classifier: Programming Language :: Python :: Implementation :: CPython
Classifier: Programming Language :: Python :: Implementation :: PyPy
Classifier: Topic :: Internet :: WWW/HTTP :: HTTP Servers
Classifier: Topic :: System :: Logging
Classifier: Topic :: Text Processing :: Filters
Requires-Python: >=3.8
Requires-Dist: attrs>=17.1
Requires-Dist: pydicti~=1.1
